ltr_datasets/__init__.py
ltr_datasets/datasets/__init__.py
ltr_datasets/datasets/base.py
ltr_datasets/datasets/istella.py
ltr_datasets/datasets/mslr.py
ltr_datasets/datasets/yahoo.py
ltr_datasets/transformations/__init__.py
ltr_datasets/transformations/base.py
ltr_datasets/transformations/filter.py
ltr_datasets/transformations/normalize.py
ltr_datasets/transformations/truncate.py
ltr_datasets/util/__init__.py
ltr_datasets/util/file.py
ltr_datasets/util/svmlight.py
ltr_datasets-0.1.3.dist-info/METADATA
ltr_datasets-0.1.3.dist-info/WHEEL
ltr_datasets-0.1.3.dist-info/RECORD
