Metadata-Version: 2.1
Name: ltr-datasets
Version: 0.1.3
Summary: 
Author: Philipp Hager
Author-email: philipp.konstantin.hager@gmail.com
Requires-Python: >=3.11,<4.0
Classifier: Programming Language :: Python :: 3
Classifier: Programming Language :: Python :: 3.11
Requires-Dist: pandas (>=2.0.3,<3.0.0)
Requires-Dist: pyarrow (>=13.0.0,<14.0.0)
Requires-Dist: scikit-learn (>=1.3.0,<2.0.0)
Requires-Dist: torch (>=2.0.1,<3.0.0)
Requires-Dist: wget (>=3.2,<4.0)
